<?xml version="1.0" encoding="utf-8" ?>
<dwsync>
<file name="main.css" server="192.168.1.11:2100/childrenshut/" local="132318497456355383" remote="132319446600000000" Dst="2" />
<file name="main.css" server="ftp-locagarden.alwaysdata.net" local="132318497456355383" remote="132318517200000000" Dst="2" />
<file name="main.css" server="ftp-locagarden.alwaysdata.net/www/" local="132327227372232319" remote="132327188400000000" Dst="2" />
<file name="main.css" server="192.168.1.11:2100//childrenshut/" local="132318497456355383" remote="132319419000000000" Dst="2" />
<file name="main.css" server="192.168.1.11:2100/portal/childrenshut/" local="132327276679898717" remote="132327204600000000" Dst="2" />
<file name="fifi.css" server="192.168.1.11:2100/portal/childrenshut/" local="132327258061012452" remote="132327186600000000" Dst="2" />
<file name="currentStyle.css" server="192.168.1.11:2100/portal/childrenshut/" local="132324788165075742" remote="132324720000000000" Dst="2" />
<file name="currentStyle.css" server="ftp-locagarden.alwaysdata.net/www/" local="132324788165075742" remote="132327188400000000" Dst="2" />
<file name="fifi.css" server="ftp-locagarden.alwaysdata.net/www/" local="132327258061012452" remote="132327188400000000" Dst="2" />
</dwsync>